ngetesdoang123.py
ngetesdoang123-0.1.1.dist-info/METADATA
ngetesdoang123-0.1.1.dist-info/WHEEL
ngetesdoang123-0.1.1.dist-info/top_level.txt
ngetesdoang123-0.1.1.dist-info/RECORD
