Metadata-Version: 2.4
Name: ngetesdoang123
Version: 0.1.1
Summary: A simple hello world Python package.
Requires-Python: >=3.13
